keras_fsl/__init__.py
keras_fsl/callbacks/__init__.py
keras_fsl/callbacks/binary_statistics.py
keras_fsl/callbacks/tensorboard_save_figures.py
keras_fsl/dataframe/__init__.py
keras_fsl/dataframe/operators/__init__.py
keras_fsl/dataframe/operators/abstract_operator.py
keras_fsl/dataframe/operators/naive_max_proba.py
keras_fsl/dataframe/operators/random_assignment.py
keras_fsl/dataframe/operators/to_k_shot_dataset.py
keras_fsl/imgaug/sequentials/__init__.py
keras_fsl/imgaug/sequentials/yolo.py
keras_fsl/layers/__init__.py
keras_fsl/layers/centroids_matrix.py
keras_fsl/layers/classification.py
keras_fsl/layers/gram_matrix.py
keras_fsl/layers/slicing.py
keras_fsl/layers/support_layer.py
keras_fsl/layers/tests/__init__.py
keras_fsl/layers/tests/centroids_matrix_test.py
keras_fsl/layers/tests/gram_matrix_test.py
keras_fsl/losses/__init__.py
keras_fsl/losses/gram_matrix_losses.py
keras_fsl/losses/tests/gram_matrix_losses_test.py
keras_fsl/metrics/__init__.py
keras_fsl/metrics/gram_matrix_metrics.py
keras_fsl/metrics/tests/__init__.py
keras_fsl/metrics/tests/gram_matrix_metrics_test.py
keras_fsl/models/__init__.py
keras_fsl/models/encoders/__init__.py
keras_fsl/models/encoders/basic_cnn.py
keras_fsl/models/encoders/darknet.py
keras_fsl/models/encoders/koch_net.py
keras_fsl/models/encoders/single_conv_2d.py
keras_fsl/models/encoders/vinyals_net.py
keras_fsl/models/head_models/__init__.py
keras_fsl/models/head_models/dense_sigmoid.py
keras_fsl/models/head_models/learnt_norms.py
keras_fsl/models/head_models/mixed_norms.py
keras_fsl/models/head_models/tests/learnt_norms_test.py
keras_fsl/models/siamese_nets.py
keras_fsl/sequences/abstract_sequence.py
keras_fsl/sequences/prediction/__init__.py
keras_fsl/sequences/prediction/pairs/__init__.py
keras_fsl/sequences/prediction/pairs/product_sequence.py
keras_fsl/sequences/prediction/single/__init__.py
keras_fsl/sequences/prediction/single/deterministic_sequence.py
keras_fsl/sequences/training/__init__.py
keras_fsl-0.2.0.dist-info/WHEEL
keras_fsl-0.2.0.dist-info/METADATA
keras_fsl-0.2.0.dist-info/RECORD
